flexsweep/__init__.py
flexsweep/balancing.py
flexsweep/cnn.py
flexsweep/data/ceu_spiedel_2019_full.yaml
flexsweep/data/chb_spiedel_2019_full.yaml
flexsweep/data/constant.yaml
flexsweep/data/decode_sexavg_2019.txt.gz
flexsweep/data/discoal
flexsweep/data/yri_spiedel_2019_full.yaml
flexsweep/data.py
flexsweep/fv.py
flexsweep/main.py
flexsweep/simulate_discoal.py
flexsweep/test/beta.py
flexsweep/test/cnn_local.py
flexsweep/test/cnn_optimization.py
flexsweep/test/cnn_test.py
flexsweep/test/fv_tests.py
flexsweep/test/fv_tucson.py
flexsweep/test/mu_stat.py
flexsweep/test/neutral_numba.py
flexsweep-1.3.dist-info/METADATA
flexsweep-1.3.dist-info/WHEEL
flexsweep-1.3.dist-info/entry_points.txt
flexsweep-1.3.dist-info/RECORD
