Metadata-Version: 2.3
Name: flexsweep
Version: 1.3
Summary: 
License: MIT
Author: Jesus Murga-Moreno
Author-email: murgamoreno@gmail.com
Requires-Python: >=3.12
Classifier: License :: OSI Approved :: MIT License
Classifier: Programming Language :: Python :: 3
Classifier: Programming Language :: Python :: 3.12
Classifier: Programming Language :: Python :: 3.13
Requires-Dist: click (>=8.1.7,<9.0.0)
Requires-Dist: demes (>=0.2.3,<0.3.0)
Requires-Dist: joblib (>=1.4.2,<2.0.0)
Requires-Dist: matplotlib (>=3.9.2,<4.0.0)
Requires-Dist: numba (>=0.60.0,<0.61.0)
Requires-Dist: numpy (==1.26.4)
Requires-Dist: polars (>=1.14.0,<2.0.0)
Requires-Dist: pyarrow (>=17.0.0,<18.0.0)
Requires-Dist: pybedtools (>=0.12.0,<0.13.0)
Requires-Dist: scikit-allel (>=1.3.8,<2.0.0)
Requires-Dist: scikit-learn (>=1.5.1,<2.0.0)
Requires-Dist: scipy (>=1.14.0,<2.0.0)
Requires-Dist: tbb (>=2022.1.0,<2023.0.0)
Requires-Dist: tensorflow[and-cuda] (>=2.18.0,<3.0.0)
Requires-Dist: threadpoolctl (>=3.5.0,<4.0.0)
Project-URL: Homepage, https://github.com/jmurga/flexsweep
Project-URL: Repository, https://github.com/jmurga/flexsweep
